DESCRIPTION.rst
LICENSE.txt
MANIFEST.in
index.html
luhn.py
luhnProofFunction.py
setup.cfg
setup.py
luhn/__init__.py
luhn/luhn.py
luhn_algorithm_validator.egg-info/PKG-INFO
luhn_algorithm_validator.egg-info/SOURCES.txt
luhn_algorithm_validator.egg-info/dependency_links.txt
luhn_algorithm_validator.egg-info/top_level.txt