Metadata-Version: 1.1
Name: luhn-algorithm-validator
Version: 1.0.1
Summary: Luhn Account Number Validator
Home-page: https://github.com/garwoodpr/LuhnAlgorithmProof
Author: Clint Garwood
Author-email: clint@garwoodpr.com
License: MIT
Keywords: Luhn Algorithm,account number validation,credit card validation,text analysis,information processing,data verification,cryptography,numerical decoding
Platform: UNKNOWN
Classifier: Development Status :: 3 - Alpha
Classifier: Topic :: Text Processing :: General
Classifier: Topic :: Scientific/Engineering :: Information Analysis
Classifier: Topic :: Office/Business :: Financial
Classifier: Programming Language :: Python :: 3.4
Classifier: Operating System :: OS Independent
Classifier: Natural Language :: English
Classifier: License :: OSI Approved :: MIT License
Classifier: Intended Audience :: Customer Service
